matos_aws_provider/__init__.py
matos_aws_provider/config.py
matos_aws_provider/observation.py
matos_aws_provider/provider.py
matos_aws_provider/lib/__init__.py
matos_aws_provider/lib/auth.py
matos_aws_provider/lib/base_provider.py
matos_aws_provider/lib/factory.py
matos_aws_provider/lib/loader.py
matos_aws_provider/lib/utils.py
matos_aws_provider/plugins/__init__.py
matos_aws_provider/plugins/account.py
matos_aws_provider/plugins/acm.py
matos_aws_provider/plugins/analyzer.py
matos_aws_provider/plugins/api_gateway.py
matos_aws_provider/plugins/apphosting.py
matos_aws_provider/plugins/autoscaling.py
matos_aws_provider/plugins/cloudformation.py
matos_aws_provider/plugins/cloudfront.py
matos_aws_provider/plugins/cloudtrail.py
matos_aws_provider/plugins/cluster.py
matos_aws_provider/plugins/codebuild.py
matos_aws_provider/plugins/config_service.py
matos_aws_provider/plugins/dax.py
matos_aws_provider/plugins/disk.py
matos_aws_provider/plugins/docdb.py
matos_aws_provider/plugins/ecr.py
matos_aws_provider/plugins/ecs.py
matos_aws_provider/plugins/eip.py
matos_aws_provider/plugins/elasticache.py
matos_aws_provider/plugins/elasticsearch.py
matos_aws_provider/plugins/emr.py
matos_aws_provider/plugins/filesystem.py
matos_aws_provider/plugins/functions.py
matos_aws_provider/plugins/glue.py
matos_aws_provider/plugins/guardduty.py
matos_aws_provider/plugins/iam.py
matos_aws_provider/plugins/instance.py
matos_aws_provider/plugins/kinesis.py
matos_aws_provider/plugins/kms.py
matos_aws_provider/plugins/lb.py
matos_aws_provider/plugins/log_metrics.py
matos_aws_provider/plugins/macie.py
matos_aws_provider/plugins/network.py
matos_aws_provider/plugins/no_sql.py
matos_aws_provider/plugins/opensearch.py
matos_aws_provider/plugins/policy.py
matos_aws_provider/plugins/redshift.py
matos_aws_provider/plugins/rest_api.py
matos_aws_provider/plugins/route53.py
matos_aws_provider/plugins/route53domain.py
matos_aws_provider/plugins/s3control.py
matos_aws_provider/plugins/sagemaker.py
matos_aws_provider-1.0.10.dist-info/LICENSE
matos_aws_provider-1.0.10.dist-info/METADATA
matos_aws_provider-1.0.10.dist-info/WHEEL
matos_aws_provider-1.0.10.dist-info/top_level.txt
matos_aws_provider-1.0.10.dist-info/RECORD
