Metadata-Version: 2.1
Name: matos-aws-provider
Version: 1.0.10
Summary: Python matos aws provider
Author: matos community
Author-email: community@cloudmatos.com
Project-URL: Bug Reports, https://github.com/cloudmatos/matos-aws-provider/issues
Project-URL: Source, https://github.com/cloudmatos/matos-aws-provider
Keywords: aws,cloudsecurity,matos,cloudmatos
Classifier: Development Status :: 3 - Alpha
Classifier: Intended Audience :: Developers
Classifier: Topic :: Software Development :: Build Tools
Classifier: License :: OSI Approved :: MIT License
Classifier: Programming Language :: Python :: 3
Classifier: Programming Language :: Python :: 3.7
Classifier: Programming Language :: Python :: 3.8
Classifier: Programming Language :: Python :: 3.9
Classifier: Programming Language :: Python :: 3.10
Classifier: Programming Language :: Python :: 3 :: Only
Requires-Python: >=3.7, <4
License-File: LICENSE
Requires-Dist: structlog
Requires-Dist: kubernetes (==21.7.0)
Requires-Dist: botocore (==1.27.61)
Requires-Dist: boto3 (==1.24.61)
Requires-Dist: awscli (==1.25.62)
Provides-Extra: dev
Requires-Dist: check-manifest ; extra == 'dev'
Provides-Extra: test
Requires-Dist: coverage ; extra == 'test'
